{
  "innerCode": 200,
  "data": {
    "name": "ZM Unassign a Members Role",
    "description": "User [roles](https://support.zoom.us/hc/en-us/articles/115001078646-Role-Based-Access-Control) can have a set of permissions that allows access only to the pages a user needs to view or edit. Use this API to unassign a user's role.\n\n**Scope:** `role:write:admin`\n \n**Prerequisites:**\n* A Pro or a higher plan.",
    "Timeout": null,
    "class": [],
    "rootSettings": {
      "isCollapse": false,
      "activitySettings": [
        {
          "required": false,
          "key": "apikey",
          "label": "Apikey",
          "labelKey": "apikey_l",
          "baseType": "control",
          "controlType": "textbox",
          "value": ""
        },
        {
          "required": false,
          "key": "password1",
          "label": "Apisecret",
          "labelKey": "apisecret_l",
          "baseType": "control",
          "controlType": "password",
          "value": ""
        },
        {
          "required": false,
          "key": "roleId",
          "label": "RoleId",
          "labelKey": "roleId_l",
          "baseType": "control",
          "controlType": "textbox",
          "value": ""
        },
        {
          "required": false,
          "key": "memberId",
          "label": "MemberId",
          "labelKey": "memberId_l",
          "baseType": "control",
          "controlType": "textbox",
          "value": ""
        },
        {
          "value": "",
          "required": false,
          "key": "linekey",
          "label": "linekey",
          "labelKey": "linekey_l",
          "baseType": "control",
          "controlType": "hr"
        },
        {
          "value": "",
          "required": false,
          "key": "Jsonkeypath",
          "label": "Json keypath",
          "labelKey": "Jsonkeypath_l",
          "baseType": "control",
          "controlType": "textbox"
        }
      ],
      "index": "1",
      "label": "main",
      "labelKey": null
    }
  },
  "message": "SUCCESS"
}