{
  "innerCode": 200,
  "data": {
    "name": "AzureNetworkInterfaceAttach",
    "description": "Azure Attach a secondary Network Interface to a Virtual Machine",
    "Timeout": "00:15:00",
    "class": [],
    "rootSettings": {
      "isCollapse": false,
      "activitySettings": [
        {
          "value": "",
          "required": true,
          "key": "vmName",
          "label": "VM Name",
          "labelKey": "VM_NAME_VALUE",
          "baseType": "control",
          "controlType": "textbox"
        },
        {
          "value": "",
          "required": true,
          "key": "networkName",
          "label": "Network Name",
          "labelKey": "NETWORK_NAME_VALUE",
          "baseType": "control",
          "controlType": "textbox"
        },
        {
          "value": "",
          "required": true,
          "key": "resourceGroupName",
          "label": "Resource Group",
          "labelKey": "RESOURCE_GROUP_NAME_VALUE",
          "baseType": "control",
          "controlType": "textbox"
        },
        {
          "value": "",
          "required": true,
          "key": "subscriptionId",
          "label": "Subscription Id",
          "labelKey": "subscription_ID_VALUE",
          "baseType": "control",
          "controlType": "textbox"
        },
        {
          "value": "",
          "required": true,
          "key": "authToken_password",
          "label": "Auth token",
          "labelKey": "authToken_password",
          "styleClass": "",
          "baseType": "control",
          "controlType": "password",
          "controlOptions": null
        },
        {
          "value": "",
          "required": false,
          "key": "linekey",
          "label": "linekey",
          "labelKey": "linekey_l",
          "baseType": "control",
          "controlType": "hr"
        },
        {
          "value": "$",
          "required": false,
          "key": "Jsonkeypath",
          "label": "Json keypath",
          "labelKey": "Jsonkeypath_l",
          "baseType": "control",
          "controlType": "textbox"
        }
      ],
      "index": "1",
      "label": "main",
      "labelKey": null
    }
  },
  "message": "SUCCESS"
}