{
  "innerCode": 200,
  "data": {
    "name": "GH Delete a deployment",
    "description": "To ensure there can always be an active deployment, you can only delete an _inactive_ deployment. Anyone with `repo` or `repo_deployment` scopes can delete an inactive deployment.\n\nTo set a deployment as inactive, you must:\n\n*   Create a new deployment that is active so that the system has a record of the current state, then delete the previously active deployment.\n*   Mark the active deployment as inactive by adding any non-successful deployment status.\n\nFor more information, see \"[Create a deployment](https://developer.github.com/v3/repos/deployments/#create-a-deployment)\" and \"[Create a deployment status](https://developer.github.com/v3/repos/deployments/#create-a-deployment-status).\"",
    "Timeout": null,
    "class": [],
    "rootSettings": {
      "isCollapse": false,
      "activitySettings": [
        {
          "required": true,
          "key": "password1",
          "label": "Authorization",
          "labelKey": "authorization_l",
          "baseType": "control",
          "controlType": "password",
          "value": ""
        },
        {
          "required": false,
          "key": "Username",
          "label": "Username",
          "labelKey": "Username_l",
          "baseType": "control",
          "controlType": "textbox",
          "value": ""
        },
        {
          "required": false,
          "key": "Accept",
          "label": "Accept",
          "labelKey": "Accept_l",
          "baseType": "control",
          "controlType": "autocomplete",
          "controlOptions": [
            {
              "key": "application/vnd.github.v3+json",
              "value": "application/vnd.github.v3+json"
            },
            {
              "key": "application/vnd.github.inertia-preview+json",
              "value": "application/vnd.github.inertia-preview+json"
            }
          ],
          "value": "application/vnd.github.v3+json"
        },
        {
          "required": false,
          "key": "owner",
          "label": "Owner",
          "labelKey": "owner_l",
          "baseType": "control",
          "controlType": "textbox",
          "value": ""
        },
        {
          "required": false,
          "key": "repo",
          "label": "Repo",
          "labelKey": "repo_l",
          "baseType": "control",
          "controlType": "textbox",
          "value": ""
        },
        {
          "required": false,
          "key": "deployment_id",
          "label": "Deployment_id",
          "labelKey": "deployment_id_l",
          "baseType": "control",
          "controlType": "textbox",
          "value": ""
        },
        {
          "value": "",
          "required": false,
          "key": "linekey",
          "label": "linekey",
          "labelKey": "linekey_l",
          "baseType": "control",
          "controlType": "hr"
        },
        {
          "value": "",
          "required": false,
          "key": "Jsonkeypath",
          "label": "Json keypath",
          "labelKey": "Jsonkeypath_l",
          "baseType": "control",
          "controlType": "textbox"
        }
      ],
      "index": "1",
      "label": "main",
      "labelKey": null
    }
  },
  "message": "SUCCESS"
}